{
    "1°_Semestre": [
        {
            "nome": "Metodologia em EAD I",
            "ch": "30"
        },
        {
            "nome": "Metodologia em EAD II",
            "ch": "30"
        },
        {
            "nome": "Contabilidade Introdutória I",
            "ch": "60"
        },
        {
            "nome": "Sociologia aplicada",
            "ch": "60"
        },
        {
            "nome": "Português Instrumental",
            "ch": "60"
        },
        {
            "nome": "Filosofia e Ética",
            "ch": "60"
        },
        {
            "nome": "Matemática I",
            "ch": "60"
        }
    ],
    "2°_Semestre": [
        {
            "nome": "Instituições de Direito",
            "ch": "60"
        },
        {
            "nome": "Psicologia Aplicada",
            "ch": "60"
        },
        {
            "nome": "Estatística",
            "ch": "60"
        },
        {
            "nome": "Metodologia da Pesquisa I",
            "ch": "30"
        },
        {
            "nome": "Contabilidade Introdutória II",
            "ch": "60"
        },
        {
            "nome": "Empreendedorismo",
            "ch": "30"
        }
    ],
    "3°_Semestre": [
        {
            "nome": "Direito Empresarial",
            "ch": "60"
        },
        {
            "nome": "Contabilidade Intermediária I",
            "ch": "60"
        },
        {
            "nome": "Economia I",
            "ch": "60"
        },
        {
            "nome": "Métodos Quantitativos Aplicados",
            "ch": "60"
        },
        {
            "nome": "Optativa(s)",
            "ch": "60"
        }
    ],
    "4°_Semestre": [
        {
            "nome": "Contabilidade de Custos I",
            "ch": "60"
        },
        {
            "nome": "Contabilidade Intermediária II",
            "ch": "60"
        },
        {
            "nome": "Administração e Cultura Organizacional",
            "ch": "60"
        },
        {
            "nome": "Elementos de Análise Financeira",
            "ch": "30"
        },
        {
            "nome": "Métodos Quantitativos Aplicados II",
            "ch": "60"
        },
        {
            "nome": "Optativa",
            "ch": "30"
        }
    ],
    "5°_Semestre": [
        {
            "nome": "Contabilidade Avançada",
            "ch": "60"
        },
        {
            "nome": "Planejamento Tributário I",
            "ch": "60"
        },
        {
            "nome": "Legislação Social",
            "ch": "60"
        },
        {
            "nome": "Organização de Empresas",
            "ch": "30"
        },
        {
            "nome": "Contabilidade de Custos II",
            "ch": "60"
        },
        {
            "nome": "Optativa",
            "ch": "30"
        }
    ],
    "6°_Semestre": [
        {
            "nome": "Análise das Demonstrações Contábeis",
            "ch": "60"
        },
        {
            "nome": "Teoria da Contabilidade",
            "ch": "60"
        },
        {
            "nome": "Contabilidade Pública I",
            "ch": "60"
        },
        {
            "nome": "Contabilidade Gerencial",
            "ch": "30"
        },
        {
            "nome": "Planejamento e Controle Orçamentário",
            "ch": "30"
        },
        {
            "nome": "Optativa(s)",
            "ch": "60"
        }
    ],
    "7°_Semestre": [
        {
            "nome": "Administração Financeira",
            "ch": "60"
        },
        {
            "nome": "Auditoria I",
            "ch": "60"
        },
        {
            "nome": "Tópicos Contemporâneos em Contabilidade",
            "ch": "60"
        },
        {
            "nome": "Metodologia da Pesquisa II",
            "ch": "30"
        },
        {
            "nome": "Trabalho de Conclusão de Curso I",
            "ch": "30"
        },
        {
            "nome": "Optativa(s)",
            "ch": "60"
        }
    ],
    "8°_Semestre": [
        {
            "nome": "Perícia Contábil",
            "ch": "60"
        },
        {
            "nome": "Legislação Profissional",
            "ch": "30"
        },
        {
            "nome": "Controladoria",
            "ch": "60"
        },
        {
            "nome": "Optativas",
            "ch": "150"
        }
    ],
    "9°_Semestre": [
        {
            "nome": "Trabalho de Conclusão de Curso II",
            "ch": "200"
        },
        {
            "nome": "Prática Contábil",
            "ch": "200"
        }
    ]
}